prettyrecord
