Metadata-Version: 1.1
Name: prettyrecord
Version: 0.2
Summary: Structures like SQLAlchemy's declarative_base or Django's models in your project!
Home-page: http://github.com/skorczan/prettyrecord
Author: Andrzej Skórcz
Author-email: skorczan@gmail.com
License: MIT
Keywords: structure model declarative record
Platform: UNKNOWN
Classifier: Development Status :: 4 - Beta
Classifier: License :: OSI Approved :: MIT License
Classifier: Programming Language :: Python :: 3
Classifier: Topic :: Software Development :: Libraries
Classifier: Intended Audience :: Developers
